darlehenpy/__init__.py
darlehenpy/darlehen.py
darlehen.py-0.9.1.dist-info/LICENSE
darlehen.py-0.9.1.dist-info/METADATA
darlehen.py-0.9.1.dist-info/WHEEL
darlehen.py-0.9.1.dist-info/top_level.txt
darlehen.py-0.9.1.dist-info/RECORD
