Metadata-Version: 2.1
Name: darlehen.py
Version: 0.9.1
Summary: darlehenpy bietet Funktionen zur Berechnung eines Darlehens
Home-page: https://github.com/allaman/darlehenpy
Author: Michael Peter
Author-email: michaeljohannpeter@gmail.com
License: MIT
Classifier: Programming Language :: Python :: 3
Classifier: License :: OSI Approved :: MIT License
License-File: LICENSE
